perm/__init__.py
perm/command.py
perm/validator.py
permafrost-0.1.1.dist-info/METADATA
permafrost-0.1.1.dist-info/WHEEL
permafrost-0.1.1.dist-info/entry_points.txt
permafrost-0.1.1.dist-info/top_level.txt
permafrost-0.1.1.dist-info/RECORD
